oci_recommendation/__init__.py
oci_recommendation/functions.py
oci_recommendation/oci_client.py
oci_recommendation/utils.py
oci_recommendation-0.0.7.dist-info/LICENCE
oci_recommendation-0.0.7.dist-info/METADATA
oci_recommendation-0.0.7.dist-info/WHEEL
oci_recommendation-0.0.7.dist-info/top_level.txt
oci_recommendation-0.0.7.dist-info/RECORD
