Metadata-Version: 2.1
Name: oci-recommendation
Version: 0.0.7
Summary: provides oci recommendations
Author-email: "dheeraj.banodha" <dheerajmbanodha@gmail.com>
Classifier: Programming Language :: Python :: 3
Classifier: Operating System :: OS Independent
Requires-Python: >=3.7
License-File: LICENCE
